{"timestamp": "2021-04-04T11:55:00Z", "previous_timestamp": "2021-04-04T11:45:00Z", "next_timestamp": "2021-04-04T12:05:00Z", "data": [{"id": "619948933e5613de794acc818f33006c", "sport_key": "basketball_nba", "sport_title": "NBA", "commence_time": "2021-04-04T19:45:00Z", "home_team": "Los Angeles Clippers", "away_team": "Los Angeles Lakers", "bookmakers": [{"key": "williamhill_us", "title": "William Hill (US)", "last_update": "2021-04-04T11:49:01Z", "markets": [{"key": "totals", "last_update": "2021-04-04T11:49:01Z", "outcomes": [{"name": "Over", "price": 1.91, "point": 215.0}, {"name": "Under", "price": 1.91, "point": 215.0}]}]}, {"key": "betonlineag", "title": "BetOnline.ag", "last_update": "2021-04-04T11:47:57Z", "markets": [{"key": "totals", "last_update": "2021-04-04T11:47:57Z", "outcomes": [{"name": "Over", "price": 1.9, "point": 215.0}, {"name": "Under", "price": 1.9, "point": 215.0}]}]}, {"key": "pointsbetus", "title": "PointsBet (US)", "last_update": "2021-04-04T11:38:15Z", "markets": [{"key": "totals", "last_update": "2021-04-04T11:38:15Z", "outcomes": [{"name": "Over", "price": 1.87, "point": 215.0}, {"name": "Under", "price": 1.95, "point": 215.0}]}]}, {"key": "sugarhouse", "title": "SugarHouse", "last_update": "2021-04-04T11:49:02Z", "markets": [{"key": "totals", "last_update": "2021-04-04T11:49:02Z", "outcomes": [{"name": "Over", "price": 1.93, "point": 215.5}, {"name": "Under", "price": 1.88, "point": 215.5}]}]}, {"key": "draftkings", "title": "DraftKings", "last_update": "2021-04-04T11:49:01Z", "markets": [{"key": "totals", "last_update": "2021-04-04T11:49:01Z", "outcomes": [{"name": "Over", "price": 1.88, "point": 215.0}, {"name": "Under", "price": 1.93, "point": 215.0}]}]}, {"key": "betrivers", "title": "BetRivers", "last_update": "2021-04-04T11:47:57Z", "markets": [{"key": "totals", "last_update": "2021-04-04T11:47:57Z", "outcomes": [{"name": "Over", "price": 1.93, "point": 215.5}, {"name": "Under", "price": 1.88, "point": 215.5}]}]}, {"key": "onexbet", "title": "1xBet", "last_update": "2021-04-04T11:43:33Z", "markets": [{"key": "totals", "last_update": "2021-04-04T11:43:33Z", "outcomes": [{"name": "Over", "price": 2.03, "point": 215.5}, {"name": "Under", "price": 1.91, "point": 215.5}]}]}, {"key": "fanduel", "title": "FanDuel", "last_update": "2021-04-04T11:47:57Z", "markets": [{"key": "totals", "last_update": "2021-04-04T11:47:57Z", "outcomes": [{"name": "Over", "price": 1.91, "point": 215.0}, {"name": "Under", "price": 1.91, "point": 215.0}]}]}, {"key": "caesars", "title": "Caesars", "last_update": "2021-04-04T11:47:58Z", "markets": [{"key": "totals", "last_update": "2021-04-04T11:47:58Z", "outcomes": [{"name": "Over", "price": 1.91, "point": 215.0}, {"name": "Under", "price": 1.91, "point": 215.0}]}]}, {"key": "bovada", "title": "Bovada", "last_update": "2021-04-04T11:49:03Z", "markets": [{"key": "totals", "last_update": "2021-04-04T11:49:03Z", "outcomes": [{"name": "Over", "price": 1.91, "point": 215.0}, {"name": "Under", "price": 1.91, "point": 215.0}]}]}, {"key": "betmgm", "title": "BetMGM", "last_update": "2021-04-04T11:49:01Z", "markets": [{"key": "totals", "last_update": "2021-04-04T11:49:01Z", "outcomes": [{"name": "Over", "price": 1.87, "point": 213.5}, {"name": "Under", "price": 1.95, "point": 213.5}]}]}, {"key": "unibet", "title": "Unibet", "last_update": "2021-04-04T11:50:05Z", "markets": [{"key": "totals", "last_update": "2021-04-04T11:50:05Z", "outcomes": [{"name": "Over", "price": 1.93, "point": 215.5}, {"name": "Under", "price": 1.89, "point": 215.5}]}]}, {"key": "bookmaker", "title": "Bookmaker", "last_update": "2021-04-04T11:46:45Z", "markets": [{"key": "totals", "last_update": "2021-04-04T11:46:45Z", "outcomes": [{"name": "Over", "price": 1.95, "point": 215.5}, {"name": "Under", "price": 1.87, "point": 215.5}]}]}, {"key": "lowvig", "title": "LowVig.ag", "last_update": "2021-04-04T11:50:07Z", "markets": [{"key": "totals", "last_update": "2021-04-04T11:50:07Z", "outcomes": [{"name": "Over", "price": 1.95, "point": 213.5}, {"name": "Under", "price": 1.95, "point": 213.5}]}]}, {"key": "foxbet", "title": "FOX Bet", "last_update": "2021-04-04T11:45:31Z", "markets": [{"key": "totals", "last_update": "2021-04-04T11:45:31Z", "outcomes": [{"name": "Over", "price": 1.91, "point": 215.5}, {"name": "Under", "price": 1.91, "point": 215.5}]}]}]}, {"id": "2f19ac6dec98bdd34e11809d2fb3730b", "sport_key": "basketball_nba", "sport_title": "NBA", "commence_time": "2021-04-04T18:15:00Z", "home_team": "Chicago Bulls", "away_team": "Brooklyn Nets", "bookmakers": [{"key": "pointsbetus", "title": "PointsBet (US)", "last_update": "2021-04-04T11:38:15Z", "markets": [{"key": "totals", "last_update": "2021-04-04T11:38:15Z", "outcomes": [{"name": "Over", "price": 1.87, "point": 225.5}, {"name": "Under", "price": 1.95, "point": 225.5}]}]}, {"key": "foxbet", "title": "FOX Bet", "last_update": "2021-04-04T11:45:31Z", "markets": [{"key": "totals", "last_update": "2021-04-04T11:45:31Z", "outcomes": [{"name": "Over", "price": 1.91, "point": 226.0}, {"name": "Under", "price": 1.91, "point": 226.0}]}]}, {"key": "onexbet", "title": "1xBet", "last_update": "2021-04-04T11:43:33Z", "markets": [{"key": "totals", "last_update": "2021-04-04T11:43:33Z", "outcomes": [{"name": "Over", "price": 1.97, "point": 225.5}, {"name": "Under", "price": 1.97, "point": 225.5}]}]}, {"key": "betonlineag", "title": "BetOnline.ag", "last_update": "2021-04-04T11:47:57Z", "markets": [{"key": "totals", "last_update": "2021-04-04T11:47:57Z", "outcomes": [{"name": "Over", "price": 1.9, "point": 225.5}, {"name": "Under", "price": 1.9, "point": 225.5}]}]}, {"key": "betmgm", "title": "BetMGM", "last_update": "2021-04-04T11:49:01Z", "markets": [{"key": "totals", "last_update": "2021-04-04T11:49:01Z", "outcomes": [{"name": "Over", "price": 1.91, "point": 225.5}, {"name": "Under", "price": 1.91, "point": 225.5}]}]}, {"key": "bovada", "title": "Bovada", "last_update": "2021-04-04T11:49:03Z", "markets": [{"key": "totals", "last_update": "2021-04-04T11:49:03Z", "outcomes": [{"name": "Over", "price": 1.91, "point": 225.5}, {"name": "Under", "price": 1.91, "point": 225.5}]}]}, {"key": "lowvig", "title": "LowVig.ag", "last_update": "2021-04-04T11:50:07Z", "markets": [{"key": "totals", "last_update": "2021-04-04T11:50:07Z", "outcomes": [{"name": "Over", "price": 1.95, "point": 225.5}, {"name": "Under", "price": 1.95, "point": 225.5}]}]}]}, {"id": "f4c3fb9f26ffa21524ca4c3c749b562e", "sport_key": "basketball_nba", "sport_title": "NBA", "commence_time": "2021-04-04T22:15:00Z", "home_team": "Boston Celtics", "away_team": "Charlotte Hornets", "bookmakers": [{"key": "pointsbetus", "title": "PointsBet (US)", "last_update": "2021-04-04T11:38:15Z", "markets": [{"key": "totals", "last_update": "2021-04-04T11:38:15Z", "outcomes": [{"name": "Over", "price": 1.87, "point": 222.5}, {"name": "Under", "price": 1.95, "point": 222.5}]}]}, {"key": "foxbet", "title": "FOX Bet", "last_update": "2021-04-04T11:45:31Z", "markets": [{"key": "totals", "last_update": "2021-04-04T11:45:31Z", "outcomes": [{"name": "Over", "price": 1.91, "point": 222.0}, {"name": "Under", "price": 1.91, "point": 222.0}]}]}, {"key": "onexbet", "title": "1xBet", "last_update": "2021-04-04T11:43:33Z", "markets": [{"key": "totals", "last_update": "2021-04-04T11:43:33Z", "outcomes": [{"name": "Over", "price": 2.0, "point": 221.5}, {"name": "Under", "price": 1.94, "point": 221.5}]}]}, {"key": "betonlineag", "title": "BetOnline.ag", "last_update": "2021-04-04T11:47:57Z", "markets": [{"key": "totals", "last_update": "2021-04-04T11:47:57Z", "outcomes": [{"name": "Over", "price": 1.9, "point": 220.0}, {"name": "Under", "price": 1.9, "point": 220.0}]}]}, {"key": "betmgm", "title": "BetMGM", "last_update": "2021-04-04T11:49:01Z", "markets": [{"key": "totals", "last_update": "2021-04-04T11:49:01Z", "outcomes": [{"name": "Over", "price": 1.91, "point": 222.5}, {"name": "Under", "price": 1.91, "point": 222.5}]}]}, {"key": "lowvig", "title": "LowVig.ag", "last_update": "2021-04-04T11:50:07Z", "markets": [{"key": "totals", "last_update": "2021-04-04T11:50:07Z", "outcomes": [{"name": "Over", "price": 1.95, "point": 220.0}, {"name": "Under", "price": 1.95, "point": 220.0}]}]}, {"key": "bovada", "title": "Bovada", "last_update": "2021-04-04T11:49:03Z", "markets": [{"key": "totals", "last_update": "2021-04-04T11:49:03Z", "outcomes": [{"name": "Over", "price": 1.91, "point": 221.5}, {"name": "Under", "price": 1.91, "point": 221.5}]}]}]}, {"id": "8df61283c13cea5d45880156cfe6408e", "sport_key": "basketball_nba", "sport_title": "NBA", "commence_time": "2021-04-04T23:45:00Z", "home_team": "Atlanta Hawks", "away_team": "Golden State Warriors", "bookmakers": [{"key": "foxbet", "title": "FOX Bet", "last_update": "2021-04-04T11:45:31Z", "markets": [{"key": "totals", "last_update": "2021-04-04T11:45:31Z", "outcomes": [{"name": "Over", "price": 1.91, "point": 224.5}, {"name": "Under", "price": 1.91, "point": 224.5}]}]}, {"key": "onexbet", "title": "1xBet", "last_update": "2021-04-04T11:43:33Z", "markets": [{"key": "totals", "last_update": "2021-04-04T11:43:33Z", "outcomes": [{"name": "Over", "price": 1.97, "point": 225.5}, {"name": "Under", "price": 1.97, "point": 225.5}]}]}, {"key": "pointsbetus", "title": "PointsBet (US)", "last_update": "2021-04-04T11:38:15Z", "markets": [{"key": "totals", "last_update": "2021-04-04T11:38:15Z", "outcomes": [{"name": "Over", "price": 1.87, "point": 224.5}, {"name": "Under", "price": 1.95, "point": 224.5}]}]}, {"key": "matchbook", "title": "Matchbook", "last_update": "2021-04-04T11:46:44Z", "markets": [{"key": "totals", "last_update": "2021-04-04T11:46:44Z", "outcomes": [{"name": "Over", "price": 2.49, "point": 224.5}, {"name": "Under", "price": 1.67, "point": 224.5}]}]}, {"key": "betonlineag", "title": "BetOnline.ag", "last_update": "2021-04-04T11:47:57Z", "markets": [{"key": "totals", "last_update": "2021-04-04T11:47:57Z", "outcomes": [{"name": "Over", "price": 1.87, "point": 225.5}, {"name": "Under", "price": 1.95, "point": 225.5}]}]}, {"key": "betmgm", "title": "BetMGM", "last_update": "2021-04-04T11:49:01Z", "markets": [{"key": "totals", "last_update": "2021-04-04T11:49:01Z", "outcomes": [{"name": "Over", "price": 1.91, "point": 224.5}, {"name": "Under", "price": 1.91, "point": 224.5}]}]}, {"key": "lowvig", "title": "LowVig.ag", "last_update": "2021-04-04T11:50:07Z", "markets": [{"key": "totals", "last_update": "2021-04-04T11:50:07Z", "outcomes": [{"name": "Over", "price": 1.91, "point": 225.5}, {"name": "Under", "price": 2.0, "point": 225.5}]}]}, {"key": "bovada", "title": "Bovada", "last_update": "2021-04-04T11:49:03Z", "markets": [{"key": "totals", "last_update": "2021-04-04T11:49:03Z", "outcomes": [{"name": "Over", "price": 1.87, "point": 224.5}, {"name": "Under", "price": 1.95, "point": 224.5}]}]}]}, {"id": "65504d1748931ef30b583943aa372d97", "sport_key": "basketball_nba", "sport_title": "NBA", "commence_time": "2021-04-04T23:15:00Z", "home_team": "Philadelphia 76ers", "away_team": "Memphis Grizzlies", "bookmakers": [{"key": "pointsbetus", "title": "PointsBet (US)", "last_update": "2021-04-04T11:38:15Z", "markets": [{"key": "totals", "last_update": "2021-04-04T11:38:15Z", "outcomes": [{"name": "Over", "price": 1.87, "point": 223.5}, {"name": "Under", "price": 1.95, "point": 223.5}]}]}, {"key": "betonlineag", "title": "BetOnline.ag", "last_update": "2021-04-04T11:47:57Z", "markets": [{"key": "totals", "last_update": "2021-04-04T11:47:57Z", "outcomes": [{"name": "Over", "price": 1.9, "point": 224.5}, {"name": "Under", "price": 1.9, "point": 224.5}]}]}, {"key": "foxbet", "title": "FOX Bet", "last_update": "2021-04-04T11:45:31Z", "markets": [{"key": "totals", "last_update": "2021-04-04T11:45:31Z", "outcomes": [{"name": "Over", "price": 1.91, "point": 224.5}, {"name": "Under", "price": 1.91, "point": 224.5}]}]}, {"key": "betmgm", "title": "BetMGM", "last_update": "2021-04-04T11:49:01Z", "markets": [{"key": "totals", "last_update": "2021-04-04T11:49:01Z", "outcomes": [{"name": "Over", "price": 1.91, "point": 223.5}, {"name": "Under", "price": 1.91, "point": 223.5}]}]}, {"key": "onexbet", "title": "1xBet", "last_update": "2021-04-04T11:43:33Z", "markets": [{"key": "totals", "last_update": "2021-04-04T11:43:33Z", "outcomes": [{"name": "Over", "price": 1.96, "point": 223.5}, {"name": "Under", "price": 1.98, "point": 223.5}]}]}, {"key": "lowvig", "title": "LowVig.ag", "last_update": "2021-04-04T11:50:07Z", "markets": [{"key": "totals", "last_update": "2021-04-04T11:50:07Z", "outcomes": [{"name": "Over", "price": 1.95, "point": 224.5}, {"name": "Under", "price": 1.95, "point": 224.5}]}]}, {"key": "bovada", "title": "Bovada", "last_update": "2021-04-04T11:49:03Z", "markets": [{"key": "totals", "last_update": "2021-04-04T11:49:03Z", "outcomes": [{"name": "Over", "price": 1.91, "point": 223.5}, {"name": "Under", "price": 1.91, "point": 223.5}]}]}]}, {"id": "93f8b587858efd6f70ce24426a099ad8", "sport_key": "basketball_nba", "sport_title": "NBA", "commence_time": "2021-04-05T02:15:00Z", "home_team": "Denver Nuggets", "away_team": "Orlando Magic", "bookmakers": [{"key": "pointsbetus", "title": "PointsBet (US)", "last_update": "2021-04-04T11:38:15Z", "markets": [{"key": "totals", "last_update": "2021-04-04T11:38:15Z", "outcomes": [{"name": "Over", "price": 1.87, "point": 215.0}, {"name": "Under", "price": 1.95, "point": 215.0}]}]}, {"key": "betonlineag", "title": "BetOnline.ag", "last_update": "2021-04-04T11:47:57Z", "markets": [{"key": "totals", "last_update": "2021-04-04T11:47:57Z", "outcomes": [{"name": "Over", "price": 1.9, "point": 215.0}, {"name": "Under", "price": 1.9, "point": 215.0}]}]}, {"key": "onexbet", "title": "1xBet", "last_update": "2021-04-04T11:43:33Z", "markets": [{"key": "totals", "last_update": "2021-04-04T11:43:33Z", "outcomes": [{"name": "Over", "price": 2.0, "point": 215.5}, {"name": "Under", "price": 1.94, "point": 215.5}]}]}, {"key": "betmgm", "title": "BetMGM", "last_update": "2021-04-04T11:49:01Z", "markets": [{"key": "totals", "last_update": "2021-04-04T11:49:01Z", "outcomes": [{"name": "Over", "price": 1.87, "point": 214.5}, {"name": "Under", "price": 1.95, "point": 214.5}]}]}, {"key": "foxbet", "title": "FOX Bet", "last_update": "2021-04-04T11:45:31Z", "markets": [{"key": "totals", "last_update": "2021-04-04T11:45:31Z", "outcomes": [{"name": "Over", "price": 1.91, "point": 215.5}, {"name": "Under", "price": 1.91, "point": 215.5}]}]}, {"key": "bovada", "title": "Bovada", "last_update": "2021-04-04T11:49:03Z", "markets": [{"key": "totals", "last_update": "2021-04-04T11:49:03Z", "outcomes": [{"name": "Over", "price": 1.91, "point": 215.0}, {"name": "Under", "price": 1.91, "point": 215.0}]}]}, {"key": "lowvig", "title": "LowVig.ag", "last_update": "2021-04-04T11:50:07Z", "markets": [{"key": "totals", "last_update": "2021-04-04T11:50:07Z", "outcomes": [{"name": "Over", "price": 1.95, "point": 215.0}, {"name": "Under", "price": 1.95, "point": 215.0}]}]}]}, {"id": "a4d2349a697a0ad6f60ecfdf20c0368f", "sport_key": "basketball_nba", "sport_title": "NBA", "commence_time": "2021-04-05T00:15:00Z", "home_team": "Houston Rockets", "away_team": "New Orleans Pelicans", "bookmakers": [{"key": "pointsbetus", "title": "PointsBet (US)", "last_update": "2021-04-04T11:38:15Z", "markets": [{"key": "totals", "last_update": "2021-04-04T11:38:15Z", "outcomes": [{"name": "Over", "price": 1.87, "point": 222.5}, {"name": "Under", "price": 1.95, "point": 222.5}]}]}, {"key": "betonlineag", "title": "BetOnline.ag", "last_update": "2021-04-04T11:47:57Z", "markets": [{"key": "totals", "last_update": "2021-04-04T11:47:57Z", "outcomes": [{"name": "Over", "price": 1.9, "point": 222.5}, {"name": "Under", "price": 1.9, "point": 222.5}]}]}, {"key": "foxbet", "title": "FOX Bet", "last_update": "2021-04-04T11:45:31Z", "markets": [{"key": "totals", "last_update": "2021-04-04T11:45:31Z", "outcomes": [{"name": "Over", "price": 1.91, "point": 222.5}, {"name": "Under", "price": 1.91, "point": 222.5}]}]}, {"key": "betmgm", "title": "BetMGM", "last_update": "2021-04-04T11:49:01Z", "markets": [{"key": "totals", "last_update": "2021-04-04T11:49:01Z", "outcomes": [{"name": "Over", "price": 1.91, "point": 221.5}, {"name": "Under", "price": 1.91, "point": 221.5}]}]}, {"key": "onexbet", "title": "1xBet", "last_update": "2021-04-04T11:43:33Z", "markets": [{"key": "totals", "last_update": "2021-04-04T11:43:33Z", "outcomes": [{"name": "Over", "price": 1.99, "point": 222.5}, {"name": "Under", "price": 1.95, "point": 222.5}]}]}, {"key": "bovada", "title": "Bovada", "last_update": "2021-04-04T11:49:03Z", "markets": [{"key": "totals", "last_update": "2021-04-04T11:49:03Z", "outcomes": [{"name": "Over", "price": 1.91, "point": 222.5}, {"name": "Under", "price": 1.91, "point": 222.5}]}]}, {"key": "lowvig", "title": "LowVig.ag", "last_update": "2021-04-04T11:50:07Z", "markets": [{"key": "totals", "last_update": "2021-04-04T11:50:07Z", "outcomes": [{"name": "Over", "price": 1.95, "point": 222.5}, {"name": "Under", "price": 1.95, "point": 222.5}]}]}]}]}