{"timestamp": "2022-01-14T11:55:00Z", "previous_timestamp": "2022-01-14T11:45:00Z", "next_timestamp": "2022-01-14T12:05:00Z", "data": [{"id": "0ace381b58c70267f7b8ee4a596b2c90", "sport_key": "basketball_nba", "sport_title": "NBA", "commence_time": "2022-01-15T00:05:00Z", "home_team": "Philadelphia 76ers", "away_team": "Boston Celtics", "bookmakers": [{"key": "onexbet", "title": "1xBet", "last_update": "2022-01-14T11:48:01Z", "markets": [{"key": "totals", "last_update": "2022-01-14T11:48:01Z", "outcomes": [{"name": "Over", "price": 1.97, "point": 212.5}, {"name": "Under", "price": 1.97, "point": 212.5}]}]}, {"key": "williamhill_us", "title": "William Hill (US)", "last_update": "2022-01-14T11:49:19Z", "markets": [{"key": "totals", "last_update": "2022-01-14T11:49:19Z", "outcomes": [{"name": "Over", "price": 1.91, "point": 212.0}, {"name": "Under", "price": 1.91, "point": 212.0}]}]}, {"key": "sugarhouse", "title": "SugarHouse", "last_update": "2022-01-14T11:49:14Z", "markets": [{"key": "totals", "last_update": "2022-01-14T11:49:14Z", "outcomes": [{"name": "Over", "price": 1.89, "point": 212.0}, {"name": "Under", "price": 1.92, "point": 212.0}]}]}, {"key": "betrivers", "title": "BetRivers", "last_update": "2022-01-14T11:49:06Z", "markets": [{"key": "totals", "last_update": "2022-01-14T11:49:06Z", "outcomes": [{"name": "Over", "price": 1.89, "point": 212.0}, {"name": "Under", "price": 1.92, "point": 212.0}]}]}, {"key": "draftkings", "title": "DraftKings", "last_update": "2022-01-14T11:47:30Z", "markets": [{"key": "totals", "last_update": "2022-01-14T11:47:30Z", "outcomes": [{"name": "Over", "price": 1.87, "point": 212.0}, {"name": "Under", "price": 1.95, "point": 212.0}]}]}, {"key": "twinspires", "title": "TwinSpires", "last_update": "2022-01-14T11:49:44Z", "markets": [{"key": "totals", "last_update": "2022-01-14T11:49:44Z", "outcomes": [{"name": "Over", "price": 1.89, "point": 212.0}, {"name": "Under", "price": 1.92, "point": 212.0}]}]}, {"key": "betonlineag", "title": "BetOnline.ag", "last_update": "2022-01-14T11:48:56Z", "markets": [{"key": "totals", "last_update": "2022-01-14T11:48:56Z", "outcomes": [{"name": "Over", "price": 1.9, "point": 212.0}, {"name": "Under", "price": 1.9, "point": 212.0}]}]}, {"key": "wynnbet", "title": "WynnBET", "last_update": "2022-01-14T11:49:14Z", "markets": [{"key": "totals", "last_update": "2022-01-14T11:49:14Z", "outcomes": [{"name": "Over", "price": 1.91, "point": 211.5}, {"name": "Under", "price": 1.91, "point": 211.5}]}]}, {"key": "betmgm", "title": "BetMGM", "last_update": "2022-01-14T11:48:58Z", "markets": [{"key": "totals", "last_update": "2022-01-14T11:48:58Z", "outcomes": [{"name": "Over", "price": 1.91, "point": 212.5}, {"name": "Under", "price": 1.91, "point": 212.5}]}]}, {"key": "barstool", "title": "Barstool Sportsbook", "last_update": "2022-01-14T11:49:47Z", "markets": [{"key": "totals", "last_update": "2022-01-14T11:49:47Z", "outcomes": [{"name": "Over", "price": 1.89, "point": 212.0}, {"name": "Under", "price": 1.92, "point": 212.0}]}]}, {"key": "foxbet", "title": "FOX Bet", "last_update": "2022-01-14T11:47:13Z", "markets": [{"key": "totals", "last_update": "2022-01-14T11:47:13Z", "outcomes": [{"name": "Over", "price": 1.85, "point": 212.0}, {"name": "Under", "price": 2.0, "point": 212.0}]}]}, {"key": "fanduel", "title": "FanDuel", "last_update": "2022-01-14T11:49:19Z", "markets": [{"key": "totals", "last_update": "2022-01-14T11:49:19Z", "outcomes": [{"name": "Over", "price": 1.91, "point": 211.5}, {"name": "Under", "price": 1.91, "point": 211.5}]}]}, {"key": "sport888", "title": "888sport", "last_update": "2022-01-14T11:48:22Z", "markets": [{"key": "totals", "last_update": "2022-01-14T11:48:22Z", "outcomes": [{"name": "Over", "price": 1.9, "point": 212.0}, {"name": "Under", "price": 1.92, "point": 212.0}]}]}, {"key": "bovada", "title": "Bovada", "last_update": "2022-01-14T11:50:06Z", "markets": [{"key": "totals", "last_update": "2022-01-14T11:50:06Z", "outcomes": [{"name": "Over", "price": 1.91, "point": 212.5}, {"name": "Under", "price": 1.91, "point": 212.5}]}]}, {"key": "unibet", "title": "Unibet", "last_update": "2022-01-14T11:46:15Z", "markets": [{"key": "totals", "last_update": "2022-01-14T11:46:15Z", "outcomes": [{"name": "Over", "price": 1.9, "point": 212.0}, {"name": "Under", "price": 1.92, "point": 212.0}]}]}, {"key": "gtbets", "title": "GTbets", "last_update": "2022-01-14T11:47:08Z", "markets": [{"key": "totals", "last_update": "2022-01-14T11:47:08Z", "outcomes": [{"name": "Over", "price": 1.92, "point": 212.0}, {"name": "Under", "price": 1.92, "point": 212.0}]}]}]}, {"id": "d268efec29056ba2e8b174258d504ba2", "sport_key": "basketball_nba", "sport_title": "NBA", "commence_time": "2022-01-15T00:10:00Z", "home_team": "Charlotte Hornets", "away_team": "Orlando Magic", "bookmakers": [{"key": "draftkings", "title": "DraftKings", "last_update": "2022-01-14T11:47:30Z", "markets": [{"key": "totals", "last_update": "2022-01-14T11:47:30Z", "outcomes": [{"name": "Over", "price": 1.91, "point": 224.0}, {"name": "Under", "price": 1.91, "point": 224.0}]}]}, {"key": "onexbet", "title": "1xBet", "last_update": "2022-01-14T11:48:01Z", "markets": [{"key": "totals", "last_update": "2022-01-14T11:48:01Z", "outcomes": [{"name": "Over", "price": 1.97, "point": 224.5}, {"name": "Under", "price": 1.97, "point": 224.5}]}]}, {"key": "fanduel", "title": "FanDuel", "last_update": "2022-01-14T11:49:19Z", "markets": [{"key": "totals", "last_update": "2022-01-14T11:49:19Z", "outcomes": [{"name": "Over", "price": 1.91, "point": 224.5}, {"name": "Under", "price": 1.91, "point": 224.5}]}]}, {"key": "wynnbet", "title": "WynnBET", "last_update": "2022-01-14T11:49:14Z", "markets": [{"key": "totals", "last_update": "2022-01-14T11:49:14Z", "outcomes": [{"name": "Over", "price": 1.91, "point": 225.0}, {"name": "Under", "price": 1.91, "point": 225.0}]}]}, {"key": "betmgm", "title": "BetMGM", "last_update": "2022-01-14T11:48:58Z", "markets": [{"key": "totals", "last_update": "2022-01-14T11:48:58Z", "outcomes": [{"name": "Over", "price": 1.91, "point": 224.5}, {"name": "Under", "price": 1.91, "point": 224.5}]}]}, {"key": "foxbet", "title": "FOX Bet", "last_update": "2022-01-14T11:47:13Z", "markets": [{"key": "totals", "last_update": "2022-01-14T11:47:13Z", "outcomes": [{"name": "Over", "price": 1.91, "point": 224.5}, {"name": "Under", "price": 1.91, "point": 224.5}]}]}, {"key": "williamhill_us", "title": "William Hill (US)", "last_update": "2022-01-14T11:49:19Z", "markets": [{"key": "totals", "last_update": "2022-01-14T11:49:19Z", "outcomes": [{"name": "Over", "price": 1.91, "point": 224.0}, {"name": "Under", "price": 1.91, "point": 224.0}]}]}, {"key": "twinspires", "title": "TwinSpires", "last_update": "2022-01-14T11:49:44Z", "markets": [{"key": "totals", "last_update": "2022-01-14T11:49:44Z", "outcomes": [{"name": "Over", "price": 1.91, "point": 224.0}, {"name": "Under", "price": 1.91, "point": 224.0}]}]}, {"key": "sugarhouse", "title": "SugarHouse", "last_update": "2022-01-14T11:49:14Z", "markets": [{"key": "totals", "last_update": "2022-01-14T11:49:14Z", "outcomes": [{"name": "Over", "price": 1.91, "point": 224.0}, {"name": "Under", "price": 1.91, "point": 224.0}]}]}, {"key": "betrivers", "title": "BetRivers", "last_update": "2022-01-14T11:49:06Z", "markets": [{"key": "totals", "last_update": "2022-01-14T11:49:06Z", "outcomes": [{"name": "Over", "price": 1.91, "point": 224.0}, {"name": "Under", "price": 1.91, "point": 224.0}]}]}, {"key": "barstool", "title": "Barstool Sportsbook", "last_update": "2022-01-14T11:49:47Z", "markets": [{"key": "totals", "last_update": "2022-01-14T11:49:47Z", "outcomes": [{"name": "Over", "price": 1.91, "point": 224.0}, {"name": "Under", "price": 1.91, "point": 224.0}]}]}, {"key": "sport888", "title": "888sport", "last_update": "2022-01-14T11:48:22Z", "markets": [{"key": "totals", "last_update": "2022-01-14T11:48:22Z", "outcomes": [{"name": "Over", "price": 1.91, "point": 224.0}, {"name": "Under", "price": 1.91, "point": 224.0}]}]}, {"key": "unibet", "title": "Unibet", "last_update": "2022-01-14T11:46:15Z", "markets": [{"key": "totals", "last_update": "2022-01-14T11:46:15Z", "outcomes": [{"name": "Over", "price": 1.91, "point": 224.0}, {"name": "Under", "price": 1.91, "point": 224.0}]}]}, {"key": "matchbook", "title": "Matchbook", "last_update": "2022-01-14T11:48:50Z", "markets": [{"key": "totals", "last_update": "2022-01-14T11:48:50Z", "outcomes": [{"name": "Over", "price": 1.56, "point": 224.5}, {"name": "Under", "price": 1.51, "point": 224.5}]}]}, {"key": "bovada", "title": "Bovada", "last_update": "2022-01-14T11:50:06Z", "markets": [{"key": "totals", "last_update": "2022-01-14T11:50:06Z", "outcomes": [{"name": "Over", "price": 1.91, "point": 224.0}, {"name": "Under", "price": 1.91, "point": 224.0}]}]}, {"key": "gtbets", "title": "GTbets", "last_update": "2022-01-14T11:47:08Z", "markets": [{"key": "totals", "last_update": "2022-01-14T11:47:08Z", "outcomes": [{"name": "Over", "price": 1.92, "point": 224.0}, {"name": "Under", "price": 1.92, "point": 224.0}]}]}]}, {"id": "baa47a75fb5eb888e528012693ef68af", "sport_key": "basketball_nba", "sport_title": "NBA", "commence_time": "2022-01-15T00:10:00Z", "home_team": "Detroit Pistons", "away_team": "Toronto Raptors", "bookmakers": [{"key": "wynnbet", "title": "WynnBET", "last_update": "2022-01-14T11:49:14Z", "markets": [{"key": "totals", "last_update": "2022-01-14T11:49:14Z", "outcomes": [{"name": "Over", "price": 1.91, "point": 215.0}, {"name": "Under", "price": 1.91, "point": 215.0}]}]}, {"key": "foxbet", "title": "FOX Bet", "last_update": "2022-01-14T11:47:13Z", "markets": [{"key": "totals", "last_update": "2022-01-14T11:47:13Z", "outcomes": [{"name": "Over", "price": 1.91, "point": 215.0}, {"name": "Under", "price": 1.91, "point": 215.0}]}]}, {"key": "fanduel", "title": "FanDuel", "last_update": "2022-01-14T11:49:19Z", "markets": [{"key": "totals", "last_update": "2022-01-14T11:49:19Z", "outcomes": [{"name": "Over", "price": 1.91, "point": 214.5}, {"name": "Under", "price": 1.91, "point": 214.5}]}]}, {"key": "matchbook", "title": "Matchbook", "last_update": "2022-01-14T11:48:50Z", "markets": [{"key": "totals", "last_update": "2022-01-14T11:48:50Z", "outcomes": [{"name": "Over", "price": 1.66, "point": 214.5}, {"name": "Under", "price": 1.74, "point": 214.5}]}]}, {"key": "williamhill_us", "title": "William Hill (US)", "last_update": "2022-01-14T11:49:19Z", "markets": [{"key": "totals", "last_update": "2022-01-14T11:49:19Z", "outcomes": [{"name": "Over", "price": 1.91, "point": 215.5}, {"name": "Under", "price": 1.91, "point": 215.5}]}]}, {"key": "sugarhouse", "title": "SugarHouse", "last_update": "2022-01-14T11:49:14Z", "markets": [{"key": "totals", "last_update": "2022-01-14T11:49:14Z", "outcomes": [{"name": "Over", "price": 1.89, "point": 215.0}, {"name": "Under", "price": 1.92, "point": 215.0}]}]}, {"key": "betrivers", "title": "BetRivers", "last_update": "2022-01-14T11:49:06Z", "markets": [{"key": "totals", "last_update": "2022-01-14T11:49:06Z", "outcomes": [{"name": "Over", "price": 1.89, "point": 215.0}, {"name": "Under", "price": 1.92, "point": 215.0}]}]}, {"key": "twinspires", "title": "TwinSpires", "last_update": "2022-01-14T11:49:44Z", "markets": [{"key": "totals", "last_update": "2022-01-14T11:49:44Z", "outcomes": [{"name": "Over", "price": 1.89, "point": 215.0}, {"name": "Under", "price": 1.92, "point": 215.0}]}]}, {"key": "draftkings", "title": "DraftKings", "last_update": "2022-01-14T11:47:30Z", "markets": [{"key": "totals", "last_update": "2022-01-14T11:47:30Z", "outcomes": [{"name": "Over", "price": 1.91, "point": 215.5}, {"name": "Under", "price": 1.91, "point": 215.5}]}]}, {"key": "barstool", "title": "Barstool Sportsbook", "last_update": "2022-01-14T11:49:47Z", "markets": [{"key": "totals", "last_update": "2022-01-14T11:49:47Z", "outcomes": [{"name": "Over", "price": 1.89, "point": 215.0}, {"name": "Under", "price": 1.92, "point": 215.0}]}]}, {"key": "sport888", "title": "888sport", "last_update": "2022-01-14T11:48:22Z", "markets": [{"key": "totals", "last_update": "2022-01-14T11:48:22Z", "outcomes": [{"name": "Over", "price": 1.9, "point": 215.0}, {"name": "Under", "price": 1.92, "point": 215.0}]}]}, {"key": "betmgm", "title": "BetMGM", "last_update": "2022-01-14T11:48:58Z", "markets": [{"key": "totals", "last_update": "2022-01-14T11:48:58Z", "outcomes": [{"name": "Over", "price": 1.91, "point": 215.5}, {"name": "Under", "price": 1.91, "point": 215.5}]}]}, {"key": "bovada", "title": "Bovada", "last_update": "2022-01-14T11:50:06Z", "markets": [{"key": "totals", "last_update": "2022-01-14T11:50:06Z", "outcomes": [{"name": "Over", "price": 1.91, "point": 215.5}, {"name": "Under", "price": 1.91, "point": 215.5}]}]}, {"key": "onexbet", "title": "1xBet", "last_update": "2022-01-14T11:48:01Z", "markets": [{"key": "totals", "last_update": "2022-01-14T11:48:01Z", "outcomes": [{"name": "Over", "price": 1.97, "point": 215.5}, {"name": "Under", "price": 1.97, "point": 215.5}]}]}, {"key": "unibet", "title": "Unibet", "last_update": "2022-01-14T11:46:15Z", "markets": [{"key": "totals", "last_update": "2022-01-14T11:46:15Z", "outcomes": [{"name": "Over", "price": 1.9, "point": 215.0}, {"name": "Under", "price": 1.92, "point": 215.0}]}]}, {"key": "gtbets", "title": "GTbets", "last_update": "2022-01-14T11:47:08Z", "markets": [{"key": "totals", "last_update": "2022-01-14T11:47:08Z", "outcomes": [{"name": "Over", "price": 1.92, "point": 215.5}, {"name": "Under", "price": 1.92, "point": 215.5}]}]}]}, {"id": "ca2fa656ad083b0415b0ac3408be7067", "sport_key": "basketball_nba", "sport_title": "NBA", "commence_time": "2022-01-15T00:40:00Z", "home_team": "Chicago Bulls", "away_team": "Golden State Warriors", "bookmakers": [{"key": "williamhill_us", "title": "William Hill (US)", "last_update": "2022-01-14T11:49:19Z", "markets": [{"key": "totals", "last_update": "2022-01-14T11:49:19Z", "outcomes": [{"name": "Over", "price": 1.91, "point": 221.5}, {"name": "Under", "price": 1.91, "point": 221.5}]}]}, {"key": "draftkings", "title": "DraftKings", "last_update": "2022-01-14T11:47:30Z", "markets": [{"key": "totals", "last_update": "2022-01-14T11:47:30Z", "outcomes": [{"name": "Over", "price": 1.91, "point": 221.5}, {"name": "Under", "price": 1.91, "point": 221.5}]}]}, {"key": "sugarhouse", "title": "SugarHouse", "last_update": "2022-01-14T11:49:14Z", "markets": [{"key": "totals", "last_update": "2022-01-14T11:49:14Z", "outcomes": [{"name": "Over", "price": 1.89, "point": 221.5}, {"name": "Under", "price": 1.92, "point": 221.5}]}]}, {"key": "wynnbet", "title": "WynnBET", "last_update": "2022-01-14T11:49:14Z", "markets": [{"key": "totals", "last_update": "2022-01-14T11:49:14Z", "outcomes": [{"name": "Over", "price": 1.91, "point": 222.5}, {"name": "Under", "price": 1.91, "point": 222.5}]}]}, {"key": "foxbet", "title": "FOX Bet", "last_update": "2022-01-14T11:47:13Z", "markets": [{"key": "totals", "last_update": "2022-01-14T11:47:13Z", "outcomes": [{"name": "Over", "price": 1.91, "point": 221.5}, {"name": "Under", "price": 1.91, "point": 221.5}]}]}, {"key": "betmgm", "title": "BetMGM", "last_update": "2022-01-14T11:48:58Z", "markets": [{"key": "totals", "last_update": "2022-01-14T11:48:58Z", "outcomes": [{"name": "Over", "price": 1.91, "point": 221.5}, {"name": "Under", "price": 1.91, "point": 221.5}]}]}, {"key": "onexbet", "title": "1xBet", "last_update": "2022-01-14T11:48:01Z", "markets": [{"key": "totals", "last_update": "2022-01-14T11:48:01Z", "outcomes": [{"name": "Over", "price": 1.97, "point": 221.5}, {"name": "Under", "price": 1.97, "point": 221.5}]}]}, {"key": "fanduel", "title": "FanDuel", "last_update": "2022-01-14T11:49:19Z", "markets": [{"key": "totals", "last_update": "2022-01-14T11:49:19Z", "outcomes": [{"name": "Over", "price": 1.91, "point": 221.5}, {"name": "Under", "price": 1.91, "point": 221.5}]}]}, {"key": "matchbook", "title": "Matchbook", "last_update": "2022-01-14T11:48:50Z", "markets": [{"key": "totals", "last_update": "2022-01-14T11:48:50Z", "outcomes": [{"name": "Over", "price": 1.57, "point": 221.5}, {"name": "Under", "price": 1.55, "point": 221.5}]}]}, {"key": "betrivers", "title": "BetRivers", "last_update": "2022-01-14T11:49:06Z", "markets": [{"key": "totals", "last_update": "2022-01-14T11:49:06Z", "outcomes": [{"name": "Over", "price": 1.89, "point": 221.5}, {"name": "Under", "price": 1.92, "point": 221.5}]}]}, {"key": "twinspires", "title": "TwinSpires", "last_update": "2022-01-14T11:49:44Z", "markets": [{"key": "totals", "last_update": "2022-01-14T11:49:44Z", "outcomes": [{"name": "Over", "price": 1.89, "point": 221.5}, {"name": "Under", "price": 1.92, "point": 221.5}]}]}, {"key": "barstool", "title": "Barstool Sportsbook", "last_update": "2022-01-14T11:49:47Z", "markets": [{"key": "totals", "last_update": "2022-01-14T11:49:47Z", "outcomes": [{"name": "Over", "price": 1.89, "point": 221.5}, {"name": "Under", "price": 1.92, "point": 221.5}]}]}, {"key": "bovada", "title": "Bovada", "last_update": "2022-01-14T11:50:06Z", "markets": [{"key": "totals", "last_update": "2022-01-14T11:50:06Z", "outcomes": [{"name": "Over", "price": 1.91, "point": 221.5}, {"name": "Under", "price": 1.91, "point": 221.5}]}]}, {"key": "sport888", "title": "888sport", "last_update": "2022-01-14T11:48:22Z", "markets": [{"key": "totals", "last_update": "2022-01-14T11:48:22Z", "outcomes": [{"name": "Over", "price": 1.9, "point": 221.5}, {"name": "Under", "price": 1.92, "point": 221.5}]}]}, {"key": "gtbets", "title": "GTbets", "last_update": "2022-01-14T11:47:08Z", "markets": [{"key": "totals", "last_update": "2022-01-14T11:47:08Z", "outcomes": [{"name": "Over", "price": 1.92, "point": 221.5}, {"name": "Under", "price": 1.92, "point": 221.5}]}]}, {"key": "unibet", "title": "Unibet", "last_update": "2022-01-14T11:46:15Z", "markets": [{"key": "totals", "last_update": "2022-01-14T11:46:15Z", "outcomes": [{"name": "Over", "price": 1.9, "point": 221.5}, {"name": "Under", "price": 1.92, "point": 221.5}]}]}]}, {"id": "4dfa7d938972e7bbe41ec2c875252d4f", "sport_key": "basketball_nba", "sport_title": "NBA", "commence_time": "2022-01-15T01:10:00Z", "home_team": "Miami Heat", "away_team": "Atlanta Hawks", "bookmakers": [{"key": "draftkings", "title": "DraftKings", "last_update": "2022-01-14T11:47:30Z", "markets": [{"key": "totals", "last_update": "2022-01-14T11:47:30Z", "outcomes": [{"name": "Over", "price": 1.91, "point": 220.5}, {"name": "Under", "price": 1.91, "point": 220.5}]}]}, {"key": "fanduel", "title": "FanDuel", "last_update": "2022-01-14T11:49:19Z", "markets": [{"key": "totals", "last_update": "2022-01-14T11:49:19Z", "outcomes": [{"name": "Over", "price": 1.91, "point": 220.5}, {"name": "Under", "price": 1.91, "point": 220.5}]}]}, {"key": "onexbet", "title": "1xBet", "last_update": "2022-01-14T11:48:01Z", "markets": [{"key": "totals", "last_update": "2022-01-14T11:48:01Z", "outcomes": [{"name": "Over", "price": 1.97, "point": 220.5}, {"name": "Under", "price": 1.97, "point": 220.5}]}]}, {"key": "matchbook", "title": "Matchbook", "last_update": "2022-01-14T11:48:50Z", "markets": [{"key": "totals", "last_update": "2022-01-14T11:48:50Z", "outcomes": [{"name": "Over", "price": 1.53, "point": 220.5}, {"name": "Under", "price": 1.56, "point": 220.5}]}]}, {"key": "williamhill_us", "title": "William Hill (US)", "last_update": "2022-01-14T11:49:19Z", "markets": [{"key": "totals", "last_update": "2022-01-14T11:49:19Z", "outcomes": [{"name": "Over", "price": 1.91, "point": 220.5}, {"name": "Under", "price": 1.91, "point": 220.5}]}]}, {"key": "sugarhouse", "title": "SugarHouse", "last_update": "2022-01-14T11:49:14Z", "markets": [{"key": "totals", "last_update": "2022-01-14T11:49:14Z", "outcomes": [{"name": "Over", "price": 1.89, "point": 221.0}, {"name": "Under", "price": 1.92, "point": 221.0}]}]}, {"key": "betrivers", "title": "BetRivers", "last_update": "2022-01-14T11:49:06Z", "markets": [{"key": "totals", "last_update": "2022-01-14T11:49:06Z", "outcomes": [{"name": "Over", "price": 1.89, "point": 221.0}, {"name": "Under", "price": 1.92, "point": 221.0}]}]}, {"key": "twinspires", "title": "TwinSpires", "last_update": "2022-01-14T11:49:44Z", "markets": [{"key": "totals", "last_update": "2022-01-14T11:49:44Z", "outcomes": [{"name": "Over", "price": 1.89, "point": 221.0}, {"name": "Under", "price": 1.92, "point": 221.0}]}]}, {"key": "wynnbet", "title": "WynnBET", "last_update": "2022-01-14T11:49:14Z", "markets": [{"key": "totals", "last_update": "2022-01-14T11:49:14Z", "outcomes": [{"name": "Over", "price": 1.91, "point": 222.0}, {"name": "Under", "price": 1.91, "point": 222.0}]}]}, {"key": "betmgm", "title": "BetMGM", "last_update": "2022-01-14T11:48:58Z", "markets": [{"key": "totals", "last_update": "2022-01-14T11:48:58Z", "outcomes": [{"name": "Over", "price": 1.91, "point": 220.5}, {"name": "Under", "price": 1.91, "point": 220.5}]}]}, {"key": "sport888", "title": "888sport", "last_update": "2022-01-14T11:48:22Z", "markets": [{"key": "totals", "last_update": "2022-01-14T11:48:22Z", "outcomes": [{"name": "Over", "price": 1.9, "point": 221.0}, {"name": "Under", "price": 1.92, "point": 221.0}]}]}, {"key": "barstool", "title": "Barstool Sportsbook", "last_update": "2022-01-14T11:49:47Z", "markets": [{"key": "totals", "last_update": "2022-01-14T11:49:47Z", "outcomes": [{"name": "Over", "price": 1.89, "point": 221.0}, {"name": "Under", "price": 1.92, "point": 221.0}]}]}, {"key": "bovada", "title": "Bovada", "last_update": "2022-01-14T11:50:06Z", "markets": [{"key": "totals", "last_update": "2022-01-14T11:50:06Z", "outcomes": [{"name": "Over", "price": 1.91, "point": 220.5}, {"name": "Under", "price": 1.91, "point": 220.5}]}]}, {"key": "unibet", "title": "Unibet", "last_update": "2022-01-14T11:46:15Z", "markets": [{"key": "totals", "last_update": "2022-01-14T11:46:15Z", "outcomes": [{"name": "Over", "price": 1.9, "point": 221.0}, {"name": "Under", "price": 1.92, "point": 221.0}]}]}, {"key": "gtbets", "title": "GTbets", "last_update": "2022-01-14T11:47:08Z", "markets": [{"key": "totals", "last_update": "2022-01-14T11:47:08Z", "outcomes": [{"name": "Over", "price": 1.92, "point": 220.5}, {"name": "Under", "price": 1.92, "point": 220.5}]}]}]}, {"id": "1be020c5099d81fe156a11de53ba9627", "sport_key": "basketball_nba", "sport_title": "NBA", "commence_time": "2022-01-15T01:40:00Z", "home_team": "San Antonio Spurs", "away_team": "Cleveland Cavaliers", "bookmakers": [{"key": "williamhill_us", "title": "William Hill (US)", "last_update": "2022-01-14T11:49:19Z", "markets": [{"key": "totals", "last_update": "2022-01-14T11:49:19Z", "outcomes": [{"name": "Over", "price": 1.91, "point": 224.0}, {"name": "Under", "price": 1.91, "point": 224.0}]}]}, {"key": "betonlineag", "title": "BetOnline.ag", "last_update": "2022-01-14T11:48:56Z", "markets": [{"key": "totals", "last_update": "2022-01-14T11:48:56Z", "outcomes": [{"name": "Over", "price": 2.0, "point": 224.0}, {"name": "Under", "price": 1.83, "point": 224.0}]}]}, {"key": "draftkings", "title": "DraftKings", "last_update": "2022-01-14T11:47:30Z", "markets": [{"key": "totals", "last_update": "2022-01-14T11:47:30Z", "outcomes": [{"name": "Over", "price": 1.91, "point": 224.0}, {"name": "Under", "price": 1.91, "point": 224.0}]}]}, {"key": "twinspires", "title": "TwinSpires", "last_update": "2022-01-14T11:49:44Z", "markets": [{"key": "totals", "last_update": "2022-01-14T11:49:44Z", "outcomes": [{"name": "Over", "price": 1.91, "point": 224.0}, {"name": "Under", "price": 1.91, "point": 224.0}]}]}, {"key": "wynnbet", "title": "WynnBET", "last_update": "2022-01-14T11:49:14Z", "markets": [{"key": "totals", "last_update": "2022-01-14T11:49:14Z", "outcomes": [{"name": "Over", "price": 1.91, "point": 224.0}, {"name": "Under", "price": 1.91, "point": 224.0}]}]}, {"key": "foxbet", "title": "FOX Bet", "last_update": "2022-01-14T11:47:13Z", "markets": [{"key": "totals", "last_update": "2022-01-14T11:47:13Z", "outcomes": [{"name": "Over", "price": 1.91, "point": 224.0}, {"name": "Under", "price": 1.91, "point": 224.0}]}]}, {"key": "betmgm", "title": "BetMGM", "last_update": "2022-01-14T11:48:58Z", "markets": [{"key": "totals", "last_update": "2022-01-14T11:48:58Z", "outcomes": [{"name": "Over", "price": 1.91, "point": 224.5}, {"name": "Under", "price": 1.91, "point": 224.5}]}]}, {"key": "onexbet", "title": "1xBet", "last_update": "2022-01-14T11:48:01Z", "markets": [{"key": "totals", "last_update": "2022-01-14T11:48:01Z", "outcomes": [{"name": "Over", "price": 2.03, "point": 224.5}, {"name": "Under", "price": 1.91, "point": 224.5}]}]}, {"key": "fanduel", "title": "FanDuel", "last_update": "2022-01-14T11:49:19Z", "markets": [{"key": "totals", "last_update": "2022-01-14T11:49:19Z", "outcomes": [{"name": "Over", "price": 1.91, "point": 223.5}, {"name": "Under", "price": 1.91, "point": 223.5}]}]}, {"key": "unibet", "title": "Unibet", "last_update": "2022-01-14T11:46:15Z", "markets": [{"key": "totals", "last_update": "2022-01-14T11:46:15Z", "outcomes": [{"name": "Over", "price": 1.91, "point": 224.0}, {"name": "Under", "price": 1.91, "point": 224.0}]}]}, {"key": "barstool", "title": "Barstool Sportsbook", "last_update": "2022-01-14T11:49:47Z", "markets": [{"key": "totals", "last_update": "2022-01-14T11:49:47Z", "outcomes": [{"name": "Over", "price": 1.91, "point": 224.0}, {"name": "Under", "price": 1.91, "point": 224.0}]}]}, {"key": "matchbook", "title": "Matchbook", "last_update": "2022-01-14T11:48:50Z", "markets": [{"key": "totals", "last_update": "2022-01-14T11:48:50Z", "outcomes": [{"name": "Over", "price": 1.78, "point": 223.5}, {"name": "Under", "price": 1.61, "point": 223.5}]}]}, {"key": "sugarhouse", "title": "SugarHouse", "last_update": "2022-01-14T11:49:14Z", "markets": [{"key": "totals", "last_update": "2022-01-14T11:49:14Z", "outcomes": [{"name": "Over", "price": 1.91, "point": 224.0}, {"name": "Under", "price": 1.91, "point": 224.0}]}]}, {"key": "betrivers", "title": "BetRivers", "last_update": "2022-01-14T11:49:06Z", "markets": [{"key": "totals", "last_update": "2022-01-14T11:49:06Z", "outcomes": [{"name": "Over", "price": 1.91, "point": 224.0}, {"name": "Under", "price": 1.91, "point": 224.0}]}]}, {"key": "bovada", "title": "Bovada", "last_update": "2022-01-14T11:50:06Z", "markets": [{"key": "totals", "last_update": "2022-01-14T11:50:06Z", "outcomes": [{"name": "Over", "price": 1.91, "point": 223.5}, {"name": "Under", "price": 1.91, "point": 223.5}]}]}, {"key": "sport888", "title": "888sport", "last_update": "2022-01-14T11:48:22Z", "markets": [{"key": "totals", "last_update": "2022-01-14T11:48:22Z", "outcomes": [{"name": "Over", "price": 1.91, "point": 224.0}, {"name": "Under", "price": 1.91, "point": 224.0}]}]}, {"key": "gtbets", "title": "GTbets", "last_update": "2022-01-14T11:47:08Z", "markets": [{"key": "totals", "last_update": "2022-01-14T11:47:08Z", "outcomes": [{"name": "Over", "price": 1.92, "point": 224.0}, {"name": "Under", "price": 1.92, "point": 224.0}]}]}]}, {"id": "d4661955412a7065df236247adc90183", "sport_key": "basketball_nba", "sport_title": "NBA", "commence_time": "2022-01-15T03:10:00Z", "home_team": "Sacramento Kings", "away_team": "Houston Rockets", "bookmakers": [{"key": "betonlineag", "title": "BetOnline.ag", "last_update": "2022-01-14T11:48:56Z", "markets": [{"key": "totals", "last_update": "2022-01-14T11:48:56Z", "outcomes": [{"name": "Over", "price": 1.9, "point": 238.0}, {"name": "Under", "price": 1.9, "point": 238.0}]}]}, {"key": "wynnbet", "title": "WynnBET", "last_update": "2022-01-14T11:49:14Z", "markets": [{"key": "totals", "last_update": "2022-01-14T11:49:14Z", "outcomes": [{"name": "Over", "price": 1.91, "point": 238.5}, {"name": "Under", "price": 1.91, "point": 238.5}]}]}, {"key": "foxbet", "title": "FOX Bet", "last_update": "2022-01-14T11:47:13Z", "markets": [{"key": "totals", "last_update": "2022-01-14T11:47:13Z", "outcomes": [{"name": "Over", "price": 1.91, "point": 239.0}, {"name": "Under", "price": 1.91, "point": 239.0}]}]}, {"key": "onexbet", "title": "1xBet", "last_update": "2022-01-14T11:48:01Z", "markets": [{"key": "totals", "last_update": "2022-01-14T11:48:01Z", "outcomes": [{"name": "Over", "price": 1.97, "point": 238.5}, {"name": "Under", "price": 1.97, "point": 238.5}]}]}, {"key": "fanduel", "title": "FanDuel", "last_update": "2022-01-14T11:49:19Z", "markets": [{"key": "totals", "last_update": "2022-01-14T11:49:19Z", "outcomes": [{"name": "Over", "price": 1.91, "point": 238.5}, {"name": "Under", "price": 1.91, "point": 238.5}]}]}, {"key": "williamhill_us", "title": "William Hill (US)", "last_update": "2022-01-14T11:49:19Z", "markets": [{"key": "totals", "last_update": "2022-01-14T11:49:19Z", "outcomes": [{"name": "Over", "price": 1.91, "point": 238.5}, {"name": "Under", "price": 1.91, "point": 238.5}]}]}, {"key": "sugarhouse", "title": "SugarHouse", "last_update": "2022-01-14T11:49:14Z", "markets": [{"key": "totals", "last_update": "2022-01-14T11:49:14Z", "outcomes": [{"name": "Over", "price": 1.89, "point": 238.5}, {"name": "Under", "price": 1.92, "point": 238.5}]}]}, {"key": "betrivers", "title": "BetRivers", "last_update": "2022-01-14T11:49:06Z", "markets": [{"key": "totals", "last_update": "2022-01-14T11:49:06Z", "outcomes": [{"name": "Over", "price": 1.89, "point": 238.5}, {"name": "Under", "price": 1.92, "point": 238.5}]}]}, {"key": "draftkings", "title": "DraftKings", "last_update": "2022-01-14T11:47:30Z", "markets": [{"key": "totals", "last_update": "2022-01-14T11:47:30Z", "outcomes": [{"name": "Over", "price": 1.91, "point": 238.5}, {"name": "Under", "price": 1.91, "point": 238.5}]}]}, {"key": "twinspires", "title": "TwinSpires", "last_update": "2022-01-14T11:49:44Z", "markets": [{"key": "totals", "last_update": "2022-01-14T11:49:44Z", "outcomes": [{"name": "Over", "price": 1.89, "point": 238.5}, {"name": "Under", "price": 1.92, "point": 238.5}]}]}, {"key": "betmgm", "title": "BetMGM", "last_update": "2022-01-14T11:48:58Z", "markets": [{"key": "totals", "last_update": "2022-01-14T11:48:58Z", "outcomes": [{"name": "Over", "price": 1.91, "point": 238.5}, {"name": "Under", "price": 1.91, "point": 238.5}]}]}, {"key": "sport888", "title": "888sport", "last_update": "2022-01-14T11:48:22Z", "markets": [{"key": "totals", "last_update": "2022-01-14T11:48:22Z", "outcomes": [{"name": "Over", "price": 1.9, "point": 238.5}, {"name": "Under", "price": 1.92, "point": 238.5}]}]}, {"key": "barstool", "title": "Barstool Sportsbook", "last_update": "2022-01-14T11:49:47Z", "markets": [{"key": "totals", "last_update": "2022-01-14T11:49:47Z", "outcomes": [{"name": "Over", "price": 1.89, "point": 238.5}, {"name": "Under", "price": 1.92, "point": 238.5}]}]}, {"key": "bovada", "title": "Bovada", "last_update": "2022-01-14T11:50:06Z", "markets": [{"key": "totals", "last_update": "2022-01-14T11:50:06Z", "outcomes": [{"name": "Over", "price": 1.91, "point": 238.5}, {"name": "Under", "price": 1.91, "point": 238.5}]}]}, {"key": "unibet", "title": "Unibet", "last_update": "2022-01-14T11:46:15Z", "markets": [{"key": "totals", "last_update": "2022-01-14T11:46:15Z", "outcomes": [{"name": "Over", "price": 1.9, "point": 238.5}, {"name": "Under", "price": 1.92, "point": 238.5}]}]}, {"key": "gtbets", "title": "GTbets", "last_update": "2022-01-14T11:47:08Z", "markets": [{"key": "totals", "last_update": "2022-01-14T11:47:08Z", "outcomes": [{"name": "Over", "price": 1.92, "point": 238.5}, {"name": "Under", "price": 1.92, "point": 238.5}]}]}]}, {"id": "22d142ca7caf949ef7b63832ae2d7b85", "sport_key": "basketball_nba", "sport_title": "NBA", "commence_time": "2022-01-15T03:10:00Z", "home_team": "Memphis Grizzlies", "away_team": "Dallas Mavericks", "bookmakers": [{"key": "sugarhouse", "title": "SugarHouse", "last_update": "2022-01-14T11:49:14Z", "markets": [{"key": "totals", "last_update": "2022-01-14T11:49:14Z", "outcomes": [{"name": "Over", "price": 1.89, "point": 217.0}, {"name": "Under", "price": 1.92, "point": 217.0}]}]}, {"key": "betrivers", "title": "BetRivers", "last_update": "2022-01-14T11:49:06Z", "markets": [{"key": "totals", "last_update": "2022-01-14T11:49:06Z", "outcomes": [{"name": "Over", "price": 1.89, "point": 217.0}, {"name": "Under", "price": 1.92, "point": 217.0}]}]}, {"key": "draftkings", "title": "DraftKings", "last_update": "2022-01-14T11:47:30Z", "markets": [{"key": "totals", "last_update": "2022-01-14T11:47:30Z", "outcomes": [{"name": "Over", "price": 1.91, "point": 217.0}, {"name": "Under", "price": 1.91, "point": 217.0}]}]}, {"key": "wynnbet", "title": "WynnBET", "last_update": "2022-01-14T11:49:14Z", "markets": [{"key": "totals", "last_update": "2022-01-14T11:49:14Z", "outcomes": [{"name": "Over", "price": 1.91, "point": 217.5}, {"name": "Under", "price": 1.91, "point": 217.5}]}]}, {"key": "foxbet", "title": "FOX Bet", "last_update": "2022-01-14T11:47:13Z", "markets": [{"key": "totals", "last_update": "2022-01-14T11:47:13Z", "outcomes": [{"name": "Over", "price": 1.91, "point": 216.5}, {"name": "Under", "price": 1.91, "point": 216.5}]}]}, {"key": "betmgm", "title": "BetMGM", "last_update": "2022-01-14T11:48:58Z", "markets": [{"key": "totals", "last_update": "2022-01-14T11:48:58Z", "outcomes": [{"name": "Over", "price": 1.91, "point": 217.5}, {"name": "Under", "price": 1.91, "point": 217.5}]}]}, {"key": "sport888", "title": "888sport", "last_update": "2022-01-14T11:48:22Z", "markets": [{"key": "totals", "last_update": "2022-01-14T11:48:22Z", "outcomes": [{"name": "Over", "price": 1.9, "point": 217.0}, {"name": "Under", "price": 1.92, "point": 217.0}]}]}, {"key": "barstool", "title": "Barstool Sportsbook", "last_update": "2022-01-14T11:49:47Z", "markets": [{"key": "totals", "last_update": "2022-01-14T11:49:47Z", "outcomes": [{"name": "Over", "price": 1.89, "point": 217.0}, {"name": "Under", "price": 1.92, "point": 217.0}]}]}, {"key": "onexbet", "title": "1xBet", "last_update": "2022-01-14T11:48:01Z", "markets": [{"key": "totals", "last_update": "2022-01-14T11:48:01Z", "outcomes": [{"name": "Over", "price": 1.97, "point": 216.5}, {"name": "Under", "price": 1.97, "point": 216.5}]}]}, {"key": "fanduel", "title": "FanDuel", "last_update": "2022-01-14T11:49:19Z", "markets": [{"key": "totals", "last_update": "2022-01-14T11:49:19Z", "outcomes": [{"name": "Over", "price": 1.91, "point": 217.0}, {"name": "Under", "price": 1.91, "point": 217.0}]}]}, {"key": "unibet", "title": "Unibet", "last_update": "2022-01-14T11:46:15Z", "markets": [{"key": "totals", "last_update": "2022-01-14T11:46:15Z", "outcomes": [{"name": "Over", "price": 1.9, "point": 217.0}, {"name": "Under", "price": 1.92, "point": 217.0}]}]}, {"key": "matchbook", "title": "Matchbook", "last_update": "2022-01-14T11:48:50Z", "markets": [{"key": "totals", "last_update": "2022-01-14T11:48:50Z", "outcomes": [{"name": "Over", "price": 1.77, "point": 217.5}, {"name": "Under", "price": 2.3, "point": 217.5}]}]}, {"key": "williamhill_us", "title": "William Hill (US)", "last_update": "2022-01-14T11:49:19Z", "markets": [{"key": "totals", "last_update": "2022-01-14T11:49:19Z", "outcomes": [{"name": "Over", "price": 1.91, "point": 217.0}, {"name": "Under", "price": 1.91, "point": 217.0}]}]}, {"key": "twinspires", "title": "TwinSpires", "last_update": "2022-01-14T11:49:44Z", "markets": [{"key": "totals", "last_update": "2022-01-14T11:49:44Z", "outcomes": [{"name": "Over", "price": 1.89, "point": 217.0}, {"name": "Under", "price": 1.92, "point": 217.0}]}]}, {"key": "bovada", "title": "Bovada", "last_update": "2022-01-14T11:50:06Z", "markets": [{"key": "totals", "last_update": "2022-01-14T11:50:06Z", "outcomes": [{"name": "Over", "price": 1.91, "point": 217.0}, {"name": "Under", "price": 1.91, "point": 217.0}]}]}, {"key": "gtbets", "title": "GTbets", "last_update": "2022-01-14T11:47:08Z", "markets": [{"key": "totals", "last_update": "2022-01-14T11:47:08Z", "outcomes": [{"name": "Over", "price": 1.92, "point": 217.0}, {"name": "Under", "price": 1.92, "point": 217.0}]}]}]}, {"id": "f5508ac29505863543cd177f63e2bee2", "sport_key": "basketball_nba", "sport_title": "NBA", "commence_time": "2022-01-15T00:10:00Z", "home_team": "Indiana Pacers", "away_team": "Phoenix Suns", "bookmakers": [{"key": "betrivers", "title": "BetRivers", "last_update": "2022-01-14T11:49:06Z", "markets": [{"key": "totals", "last_update": "2022-01-14T11:49:06Z", "outcomes": [{"name": "Over", "price": 1.89, "point": 221.5}, {"name": "Under", "price": 1.92, "point": 221.5}]}]}, {"key": "twinspires", "title": "TwinSpires", "last_update": "2022-01-14T11:49:44Z", "markets": [{"key": "totals", "last_update": "2022-01-14T11:49:44Z", "outcomes": [{"name": "Over", "price": 1.89, "point": 221.5}, {"name": "Under", "price": 1.92, "point": 221.5}]}]}, {"key": "wynnbet", "title": "WynnBET", "last_update": "2022-01-14T11:49:14Z", "markets": [{"key": "totals", "last_update": "2022-01-14T11:49:14Z", "outcomes": [{"name": "Over", "price": 1.91, "point": 221.0}, {"name": "Under", "price": 1.91, "point": 221.0}]}]}, {"key": "sport888", "title": "888sport", "last_update": "2022-01-14T11:48:22Z", "markets": [{"key": "totals", "last_update": "2022-01-14T11:48:22Z", "outcomes": [{"name": "Over", "price": 1.9, "point": 221.5}, {"name": "Under", "price": 1.92, "point": 221.5}]}]}, {"key": "barstool", "title": "Barstool Sportsbook", "last_update": "2022-01-14T11:49:47Z", "markets": [{"key": "totals", "last_update": "2022-01-14T11:49:47Z", "outcomes": [{"name": "Over", "price": 1.89, "point": 221.5}, {"name": "Under", "price": 1.92, "point": 221.5}]}]}, {"key": "fanduel", "title": "FanDuel", "last_update": "2022-01-14T11:49:19Z", "markets": [{"key": "totals", "last_update": "2022-01-14T11:49:19Z", "outcomes": [{"name": "Over", "price": 1.91, "point": 221.5}, {"name": "Under", "price": 1.91, "point": 221.5}]}]}, {"key": "onexbet", "title": "1xBet", "last_update": "2022-01-14T11:48:01Z", "markets": [{"key": "totals", "last_update": "2022-01-14T11:48:01Z", "outcomes": [{"name": "Over", "price": 1.97, "point": 221.5}, {"name": "Under", "price": 1.97, "point": 221.5}]}]}, {"key": "unibet", "title": "Unibet", "last_update": "2022-01-14T11:46:15Z", "markets": [{"key": "totals", "last_update": "2022-01-14T11:46:15Z", "outcomes": [{"name": "Over", "price": 1.9, "point": 221.5}, {"name": "Under", "price": 1.92, "point": 221.5}]}]}, {"key": "sugarhouse", "title": "SugarHouse", "last_update": "2022-01-14T11:49:14Z", "markets": [{"key": "totals", "last_update": "2022-01-14T11:49:14Z", "outcomes": [{"name": "Over", "price": 1.89, "point": 221.5}, {"name": "Under", "price": 1.92, "point": 221.5}]}]}, {"key": "williamhill_us", "title": "William Hill (US)", "last_update": "2022-01-14T11:49:19Z", "markets": [{"key": "totals", "last_update": "2022-01-14T11:49:19Z", "outcomes": [{"name": "Over", "price": 1.91, "point": 221.5}, {"name": "Under", "price": 1.91, "point": 221.5}]}]}, {"key": "draftkings", "title": "DraftKings", "last_update": "2022-01-14T11:47:30Z", "markets": [{"key": "totals", "last_update": "2022-01-14T11:47:30Z", "outcomes": [{"name": "Over", "price": 1.91, "point": 221.5}, {"name": "Under", "price": 1.91, "point": 221.5}]}]}, {"key": "matchbook", "title": "Matchbook", "last_update": "2022-01-14T11:48:50Z", "markets": [{"key": "totals", "last_update": "2022-01-14T11:48:50Z", "outcomes": [{"name": "Over", "price": 1.54, "point": 221.5}, {"name": "Under", "price": 1.54, "point": 221.5}]}]}, {"key": "foxbet", "title": "FOX Bet", "last_update": "2022-01-14T11:47:13Z", "markets": [{"key": "totals", "last_update": "2022-01-14T11:47:13Z", "outcomes": [{"name": "Over", "price": 1.91, "point": 222.0}, {"name": "Under", "price": 1.91, "point": 222.0}]}]}, {"key": "betmgm", "title": "BetMGM", "last_update": "2022-01-14T11:48:58Z", "markets": [{"key": "totals", "last_update": "2022-01-14T11:48:58Z", "outcomes": [{"name": "Over", "price": 1.91, "point": 221.5}, {"name": "Under", "price": 1.91, "point": 221.5}]}]}, {"key": "bovada", "title": "Bovada", "last_update": "2022-01-14T11:50:06Z", "markets": [{"key": "totals", "last_update": "2022-01-14T11:50:06Z", "outcomes": [{"name": "Over", "price": 1.91, "point": 221.5}, {"name": "Under", "price": 1.91, "point": 221.5}]}]}, {"key": "gtbets", "title": "GTbets", "last_update": "2022-01-14T11:47:08Z", "markets": [{"key": "totals", "last_update": "2022-01-14T11:47:08Z", "outcomes": [{"name": "Over", "price": 1.92, "point": 221.5}, {"name": "Under", "price": 1.92, "point": 221.5}]}]}]}]}